{
  "contract": {
    "name": "AKC",
    "symbol": "AKC",
    "totalSupply": "300000000",
    "bytecodeSize": 4822
  },
  "gasEstimate": "972030",
  "costs": {
    "slow": {
      "gasPrice": "3",
      "bnb": "0.00291609",
      "usd_600": 1.749654,
      "krw": 2327.03982
    },
    "standard": {
      "gasPrice": "5",
      "bnb": "0.00486015",
      "usd_600": 2.9160899999999996,
      "krw": 3878.3996999999995
    },
    "fast": {
      "gasPrice": "10",
      "bnb": "0.0097203",
      "usd_600": 5.832179999999999,
      "krw": 7756.799399999999
    }
  },
  "recommended": {
    "bnb": "0.0097203",
    "usd_600": 5.832179999999999,
    "krw": 7756.799399999999
  },
  "timestamp": "2025-11-05T07:19:06.861Z"
}